register/rtl/top.v
module register (
	input wire clk,
	input wire rst_n,
	input wire wr_en,
	input wire rd_en,
	input wire [9:0] addr,
	input wire [31:0] wdata,
	output reg [31:0] rdata
);

// Define the internal register addresses 
parameter ADDR_DATA0 = 10'h0;
parameter ADDR_SR0 = 10'h4;
parameter ADDR_DATA1 = 10'h8;
parameter ADDR_SR1 = 10'hc;

// Define the internal registers
reg [31:0] data0;	 // the data0 register.
reg [31:0] sr_data0;	 // the Status data0 register.
reg [31:0] data1;	 // The data1 register.
reg [31:0] sr_data1;	// The status data1 register

initial begin
	data0 = 32'h00000000;
	sr_data0 = 32'h00000000;
	data1 = 32'hffffffff;
	sr_data1 = 32'hffffffff;
end

// writing data and update register.
always @(posedge clk or negedge rst_n) begin
	if(!rst_n) begin
		data0 <= 32'h00000000;
		sr_data0 <= 32'h00000000;
		data1 <= 32'hffffffff;
		sr_data1 <= 32'hffffffff;
		rdata <= 32'h00000000;
	end else begin
		if (wr_en && (addr == ADDR_DATA0)) begin
			data0 <= wdata; 		// write data in the data0 register.
		end else if (wr_en && (addr == ADDR_DATA1)) begin
			data1 <= wdata; 		// write data in the data1 register.
		end else if (wr_en && (addr == ADDR_SR0)) begin
			sr_data0 <= data0;
		end else if (wr_en && (addr == ADDR_SR1)) begin
			sr_data1 <= data1;
		end 

		if (rd_en) begin
			case (addr)
				ADDR_DATA0: rdata <= data0;
				ADDR_SR0: rdata <= sr_data0;
				ADDR_DATA1: rdata <= data1;
				ADDR_SR1: rdata <= sr_data1;
				default: rdata <= 32'h00000000;
			endcase
		end else begin
			rdata <= 32'h00000000;
		end
	end
end

endmodule

register/tb/test_bench.v
`timescale 1ns/1ps
module test_bench;
	reg clk;
	reg rst_n;
	reg wr_en;
	reg rd_en;
	reg [9:0] addr;
	reg [31:0] wdata;
	wire [31:0] rdata;

	register dut(
		.clk(clk),
		.rst_n(rst_n),
		.wr_en(wr_en),
		.rd_en(rd_en),
		.addr(addr),
		.wdata(wdata),
		.rdata(rdata)
	);

	initial begin
		clk = 0;
		forever #5 clk =~clk;
	end

	task verify;
		input [31:0] exp_rdata;
		begin
			$display("At time: %t, wr_en: 1'b%b, rd_en: 1'b%b, addr: 10'h%h, wdata: 32'h%h", $time, wr_en, rd_en, addr, wdata);
			if (rdata == exp_rdata) begin
				$display("------------------------------------------------------------------------------------------------------------");
				$display("PASSED: expected rdata: 32'h%h, Got rdata: 32'h%h", exp_rdata, rdata);
				$display("------------------------------------------------------------------------------------------------------------");
			end else begin
				$display("------------------------------------------------------------------------------------------------------------");
				$display("FAILDED: expected rdata: 32'h%h, Got rdata: 32'h%h", exp_rdata, rdata);
				$display("------------------------------------------------------------------------------------------------------------");
			end
		end
	endtask

	initial begin
		$dumpfile("test_bench.vcd");
		$dumpvars(0, test_bench);

		$display("---------------------------------------------------------------------------------------------------------------------------");
		$display("----------------------------------------------TESTBENCH FOR REGISTER ------------------------------------------------------");
		$display("---------------------------------------------------------------------------------------------------------------------------");

		rst_n = 0;
		wr_en = 1;
		rd_en = 0;
		addr = 10'h0;
		wdata = 32'h4;
		@(posedge clk);
		verify(32'h00000000);

		rst_n = 1;
		wr_en = 1;
		rd_en = 0;
		addr =10'h0;
		wdata = 32'hf0f0f0f0;
		@(posedge clk);
		verify(32'h00000000);

		wr_en = 0;
		rd_en = 1;
		addr = 10'h0;
		wdata = 32'hffffffff;
		@(posedge clk);
		verify(32'hf0f0f0f0);

		wr_en = 1;
		rd_en = 1;
		addr = 10'h0;
		wdata = 32'h55555555;
		@(posedge clk);
		verify(32'hf0f0f0f0);

		wr_en = 0;
		rd_en = 1;
		addr = 10'h0;
		wdata = 32'haaaaaaaa;
		@(posedge clk);
		verify(32'h55555555);

		wr_en = 1;
		rd_en = 0;
		addr = 10'h8;
		wdata = 32'h15975312;
		@(posedge clk);
		verify(32'h00000000);

		wr_en = 0;
		rd_en = 1;
		addr = 10'h8;
		wdata = 32'hffffffff;
		@(posedge clk);
		verify(32'h15975312);

		wr_en = 1;
		rd_en = 0;
		addr = 10'h4;
		wdata = 32'h11111111;
		@(posedge clk);
		verify(32'h00000000);
		
		wr_en = 0;
		rd_en = 1;
		addr = 10'h4;
		wdata = 32'h33333333;
		@(posedge clk);
		verify(32'h55555555);

		wr_en = 1;
		rd_en = 0;
		addr = 10'hc;
		wdata = 32'h7777777;
		@(posedge clk);
		verify(32'h00000000);

		wr_en = 0;
		rd_en = 1;
		addr = 32'hc;
		wdata = 32'h88888888;
		@(posedge clk);
		verify(32'h15975312);

		addr = 32'hf;
		@(posedge clk);
		verify(32'h00000000);

		$display("------------------------------------- TESTBENCH COMPLETED -------------------------------------------------");
		#100;
		$finish;
	end
endmodule

register/sim/test_bench.vcd
$date
	Wed Jan  8 00:04:15 2025
$end
$version
	Icarus Verilog
$end
$timescale
	1ps
$end
$scope module test_bench $end
$var wire 32 ! rdata [31:0] $end
$var reg 10 " addr [9:0] $end
$var reg 1 # clk $end
$var reg 1 $ rd_en $end
$var reg 1 % rst_n $end
$var reg 32 & wdata [31:0] $end
$var reg 1 ' wr_en $end
$scope module dut $end
$var wire 10 ( addr [9:0] $end
$var wire 1 # clk $end
$var wire 1 $ rd_en $end
$var wire 1 % rst_n $end
$var wire 32 ) wdata [31:0] $end
$var wire 1 ' wr_en $end
$var parameter 10 * ADDR_DATA0 $end
$var parameter 10 + ADDR_DATA1 $end
$var parameter 10 , ADDR_SR0 $end
$var parameter 10 - ADDR_SR1 $end
$var reg 32 . data0 [31:0] $end
$var reg 32 / data1 [31:0] $end
$var reg 32 0 rdata [31:0] $end
$var reg 32 1 sr_data0 [31:0] $end
$var reg 32 2 sr_data1 [31:0] $end
$upscope $end
$scope task verify $end
$var reg 32 3 exp_rdata [31:0] $end
$upscope $end
$upscope $end
$enddefinitions $end
$comment Show the parameter values. $end
$dumpall
b1100 -
b100 ,
b1000 +
b0 *
$end
#0
$dumpvars
bx 3
b11111111111111111111111111111111 2
b0 1
b0 0
b11111111111111111111111111111111 /
b0 .
b100 )
b0 (
1'
b100 &
0%
0$
0#
b0 "
b0 !
$end
#5000
b11110000111100001111000011110000 .
b11110000111100001111000011110000 &
b11110000111100001111000011110000 )
1%
b0 3
1#
#10000
0#
#15000
b11110000111100001111000011110000 !
b11110000111100001111000011110000 0
b11111111111111111111111111111111 &
b11111111111111111111111111111111 )
1$
0'
1#
#20000
0#
#25000
b1010101010101010101010101010101 .
b1010101010101010101010101010101 &
b1010101010101010101010101010101 )
1'
b11110000111100001111000011110000 3
1#
#30000
0#
#35000
b1010101010101010101010101010101 !
b1010101010101010101010101010101 0
b10101010101010101010101010101010 &
b10101010101010101010101010101010 )
0'
1#
#40000
0#
#45000
b0 !
b0 0
b10101100101110101001100010010 /
b10101100101110101001100010010 &
b10101100101110101001100010010 )
b1000 "
b1000 (
0$
1'
b1010101010101010101010101010101 3
1#
#50000
0#
#55000
b10101100101110101001100010010 !
b10101100101110101001100010010 0
b11111111111111111111111111111111 &
b11111111111111111111111111111111 )
1$
0'
b0 3
1#
#60000
0#
#65000
b0 !
b0 0
b1010101010101010101010101010101 1
b10001000100010001000100010001 &
b10001000100010001000100010001 )
b100 "
b100 (
0$
1'
b10101100101110101001100010010 3
1#
#70000
0#
#75000
b1010101010101010101010101010101 !
b1010101010101010101010101010101 0
b110011001100110011001100110011 &
b110011001100110011001100110011 )
1$
0'
b0 3
1#
#80000
0#
#85000
b0 !
b0 0
b10101100101110101001100010010 2
b111011101110111011101110111 &
b111011101110111011101110111 )
b1100 "
b1100 (
0$
1'
b1010101010101010101010101010101 3
1#
#90000
0#
#95000
b10101100101110101001100010010 !
b10101100101110101001100010010 0
b10001000100010001000100010001000 &
b10001000100010001000100010001000 )
1$
0'
b0 3
1#
#100000
0#
#105000
b0 !
b0 0
b1111 "
b1111 (
b10101100101110101001100010010 3
1#
#110000
0#
#115000
b0 3
1#
